revmut-0.3.0.dist-info/DESCRIPTION.rst
revmut-0.3.0.dist-info/metadata.json
revmut-0.3.0.dist-info/top_level.txt
revmut-0.3.0.dist-info/WHEEL
revmut-0.3.0.dist-info/dependency_links.txt
revmut-0.3.0.dist-info/RECORD
revmut-0.3.0.dist-info/METADATA
revmut-0.3.0.dist-info/entry_points.txt
revmut/verify.py
revmut/revertant_mutation_checker.py
revmut/_version.py
revmut/utils.py
revmut/__init__.py
revmut/find.py
revmut/oncotator.py
