Metadata-Version: 2.0
Name: revmut
Version: 0.3.0
Summary: REVertant MUTation finder
Home-page: https://github.com/inodb/revmut
Author: Ino de Bruijn
Author-email: ino@ino.pm
License: MIT
Keywords: Python revertant mutation finder HGVS
Platform: UNKNOWN
Classifier: Development Status :: 2 - Pre-Alpha
Classifier: Intended Audience :: Science/Research
Classifier: Natural Language :: English
Classifier: License :: OSI Approved :: MIT License
Classifier: Operating System :: OS Independent
Classifier: Programming Language :: Python
Classifier: Programming Language :: Python :: 2
Classifier: Programming Language :: Python :: 2.6
Classifier: Programming Language :: Python :: 2.7
Classifier: Topic :: Software Development :: Libraries :: Python Modules
Requires-Dist: pandas (>=0.16.1)
Requires-Dist: biopython (>=1.65)
Requires-Dist: sufam (==0.4)
